[
    {
        "id": 10,
        "data": "13/07/2025 09:12",
        "carrinho": true,
        "total": 10.0,
        "id_cliente": 6,
        "status": "Em andamento",
        "id_entregador": 9
    },
    {
        "id": 11,
        "data": "13/07/2025 09:43",
        "carrinho": true,
        "total": 142.5,
        "id_cliente": 6,
        "status": "Entregue",
        "id_entregador": 9
    },
    {
        "id": 12,
        "data": "13/07/2025 22:24",
        "carrinho": true,
        "total": 400.0,
        "id_cliente": 3,
        "status": "Entregue",
        "id_entregador": 6
    },
    {
        "id": 13,
        "data": "13/07/2025 22:24",
        "carrinho": true,
        "total": 20.0,
        "id_cliente": 6,
        "status": "Entregue",
        "id_entregador": 6
    },
    {
        "id": 14,
        "data": "13/07/2025 22:27",
        "carrinho": true,
        "total": 94.05,
        "id_cliente": 11,
        "status": "Em andamento",
        "id_entregador": 5
    },
    {
        "id": 15,
        "data": "13/07/2025 22:29",
        "carrinho": true,
        "total": 99.0,
        "id_cliente": 11,
        "status": "Em andamento",
        "id_entregador": 5
    },
    {
        "id": 16,
        "data": "13/07/2025 22:37",
        "carrinho": true,
        "total": 50180.0,
        "id_cliente": 11,
        "status": "Em andamento",
        "id_entregador": 6
    }
]